{"video_url": "https://www.youtube.com/embed/0tvX_iVSX8M?showinfo=0", "1": {"text": "Choose the freshest beets.", "img": "https://www.wikihow.com/images/thumb/d/d2/Cook-Beets-Step-1.jpg/v4-460px-Cook-Beets-Step-1.jpg", "vid": null}, "2": {"text": "Remove the beet leaves.", "img": "https://www.wikihow.com/images/thumb/9/99/Cook-Beets-Step-2.jpg/v4-460px-Cook-Beets-Step-2.jpg", "vid": null}, "3": {"text": "Trim the beets.", "img": "https://www.wikihow.com/images/thumb/4/4a/Cook-Beets-Step-3.jpg/v4-460px-Cook-Beets-Step-3.jpg", "vid": null}, "4": {"text": "Clean the beets.", "img": "https://www.wikihow.com/images/thumb/e/e0/Cook-Beets-Step-4.jpg/v4-460px-Cook-Beets-Step-4.jpg", "vid": null}, "5": {"text": "Preheat the oven to 400\u00baF (204\u00baC).", "img": "https://www.wikihow.com/images/thumb/8/85/Cook-Beets-Step-5.jpg/v4-460px-Cook-Beets-Step-5.jpg", "vid": null}, "6": {"text": "Prepare your baking sheet.", "img": "https://www.wikihow.com/images/thumb/9/97/Cook-Beets-Step-6.jpg/v4-460px-Cook-Beets-Step-6.jpg", "vid": null}, "7": {"text": "Wrap the beets in aluminum foil.", "img": "https://www.wikihow.com/images/thumb/2/2c/Cook-Beets-Step-7.jpg/v4-460px-Cook-Beets-Step-7.jpg", "vid": null}, "8": {"text": "Cook the beets in the oven for 50-60 minutes.", "img": "https://www.wikihow.com/images/thumb/5/53/Cook-Beets-Step-8.jpg/v4-460px-Cook-Beets-Step-8.jpg", "vid": null}, "9": {"text": "Add water if the beets start to scorch.", "img": "https://www.wikihow.com/images/thumb/e/ec/Cook-Beets-Step-9.jpg/v4-460px-Cook-Beets-Step-9.jpg", "vid": null}, "10": {"text": "Test the beets for doneness.", "img": "https://www.wikihow.com/images/thumb/3/3a/Cook-Beets-Step-10.jpg/v4-460px-Cook-Beets-Step-10.jpg", "vid": null}, "11": {"text": "Let them cool.", "img": "https://www.wikihow.com/images/thumb/8/8d/Cook-Beets-Step-11.jpg/v4-460px-Cook-Beets-Step-11.jpg", "vid": null}, "12": {"text": "Peel the beets.", "img": "https://www.wikihow.com/images/thumb/a/ae/Cook-Beets-Step-12.jpg/v4-460px-Cook-Beets-Step-12.jpg", "vid": null}, "13": {"text": "Serve.", "img": "https://www.wikihow.com/images/thumb/a/a1/Cook-Beets-Step-13.jpg/v4-460px-Cook-Beets-Step-13.jpg", "vid": null}, "14": {"text": "Place the beets in a microwave-safe bowl.", "img": "https://www.wikihow.com/images/thumb/2/2e/Cook-Beets-Step-14.jpg/v4-460px-Cook-Beets-Step-14.jpg", "vid": null}, "15": {"text": "Add 2 tablespoons (30 ml) of water.", "img": "https://www.wikihow.com/images/thumb/7/76/Cook-Beets-Step-15.jpg/v4-460px-Cook-Beets-Step-15.jpg", "vid": null}, "16": {"text": "Cover the beets and microwave them for 5 minutes.", "img": null, "vid": null}, "17": {"text": "Rotate the beets and microwave them for another 3-5 minutes.", "img": "https://www.wikihow.com/images/thumb/f/f9/Cook-Beets-Step-17.jpg/v4-460px-Cook-Beets-Step-17.jpg", "vid": null}, "18": {"text": "Cool the beets.", "img": "https://www.wikihow.com/images/thumb/a/a6/Cook-Beets-Step-16.jpg/v4-460px-Cook-Beets-Step-16.jpg", "vid": null}, "19": {"text": "Peel the skin.", "img": "https://www.wikihow.com/images/thumb/0/08/Cook-Beets-Step-19.jpg/v4-460px-Cook-Beets-Step-19.jpg", "vid": null}, "20": {"text": "Serve.", "img": "https://www.wikihow.com/images/thumb/4/46/Cook-Beets-Step-20.jpg/v4-460px-Cook-Beets-Step-20.jpg", "vid": null}, "21": {"text": "Peel the beets.", "img": "https://www.wikihow.com/images/thumb/0/0b/Cook-Beets-Step-21.jpg/v4-460px-Cook-Beets-Step-21.jpg", "vid": null}, "22": {"text": "Cut the beets into matchstick-size strips.", "img": "https://www.wikihow.com/images/thumb/b/b3/Cook-Beets-Step-22.jpg/v4-460px-Cook-Beets-Step-22.jpg", "vid": null}, "23": {"text": "Dust the strips with cornstarch.", "img": "https://www.wikihow.com/images/thumb/e/e9/Cook-Beets-Step-23.jpg/v4-460px-Cook-Beets-Step-23.jpg", "vid": null}, "24": {"text": "Heat vegetable oil in a medium stockpot.", "img": "https://www.wikihow.com/images/thumb/4/41/Cook-Beets-Step-24.jpg/v4-460px-Cook-Beets-Step-24.jpg", "vid": null}, "25": {"text": "Add the beet strips to the hot oil.", "img": "https://www.wikihow.com/images/thumb/9/94/Cook-Beets-Step-25.jpg/v4-460px-Cook-Beets-Step-25.jpg", "vid": null}, "26": {"text": "Remove and drain the beets.", "img": "https://www.wikihow.com/images/thumb/6/6e/Cook-Beets-Step-26.jpg/v4-460px-Cook-Beets-Step-26.jpg", "vid": null}, "27": {"text": "Serve.", "img": "https://www.wikihow.com/images/thumb/4/4c/Cook-Beets-Step-27.jpg/v4-460px-Cook-Beets-Step-27.jpg", "vid": null}, "28": {"text": "Place the beets in a large pot.", "img": "https://www.wikihow.com/images/thumb/2/25/Cook-Beets-Step-28.jpg/v4-460px-Cook-Beets-Step-28.jpg", "vid": null}, "29": {"text": "Cover them with cold water.", "img": "https://www.wikihow.com/images/thumb/8/82/Cook-Beets-Step-29.jpg/v4-460px-Cook-Beets-Step-29.jpg", "vid": null}, "30": {"text": "Add sugar and salt as needed.", "img": "https://www.wikihow.com/images/thumb/6/65/Cook-Beets-Step-30.jpg/v4-460px-Cook-Beets-Step-30.jpg", "vid": null}, "31": {"text": "Boil the water over high heat.", "img": "https://www.wikihow.com/images/thumb/b/b8/Cook-Beets-Step-31.jpg/v4-460px-Cook-Beets-Step-31.jpg", "vid": null}, "32": {"text": "Reduce the heat to medium once the water boils.", "img": "https://www.wikihow.com/images/thumb/5/50/Cook-Beets-Step-32.jpg/v4-460px-Cook-Beets-Step-32.jpg", "vid": null}, "33": {"text": "Cook the beets for 45-60 minutes until they're done.", "img": "https://www.wikihow.com/images/thumb/2/23/Cook-Beets-Step-33.jpg/v4-460px-Cook-Beets-Step-33.jpg", "vid": null}, "34": {"text": "Remove them from the heat.", "img": "https://www.wikihow.com/images/thumb/7/7a/Cook-Beets-Step-34.jpg/v4-460px-Cook-Beets-Step-34.jpg", "vid": null}, "35": {"text": "Serve.", "img": "https://www.wikihow.com/images/thumb/c/cc/Cook-Beets-Step-35.jpg/v4-460px-Cook-Beets-Step-35.jpg", "vid": null}, "36": {"text": "Fill the bottom of a steamer with 2 inches (5 cm) of water.", "img": "https://www.wikihow.com/images/thumb/9/93/Cook-Beets-Step-36.jpg/v4-460px-Cook-Beets-Step-36.jpg", "vid": null}, "37": {"text": "Bring the water to a boil.", "img": "https://www.wikihow.com/images/thumb/6/61/Cook-Beets-Step-37.jpg/v4-460px-Cook-Beets-Step-37.jpg", "vid": null}, "38": {"text": "Arrange the beets in a steamer.", "img": "https://www.wikihow.com/images/thumb/1/18/Cook-Beets-Step-38.jpg/v4-460px-Cook-Beets-Step-38.jpg", "vid": null}, "39": {"text": "Cook them for 45 minutes or until they're tender.", "img": "https://www.wikihow.com/images/thumb/2/2e/Cook-Beets-Step-39.jpg/v4-460px-Cook-Beets-Step-39.jpg", "vid": null}, "40": {"text": "Remove the beets from heat.", "img": "https://www.wikihow.com/images/thumb/b/be/Pickle-Beets-Step-3-Version-3.jpg/v4-460px-Pickle-Beets-Step-3-Version-3.jpg", "vid": null}, "41": {"text": "Serve.", "img": "https://www.wikihow.com/images/thumb/f/fe/Cook-Beets-Step-41.jpg/v4-460px-Cook-Beets-Step-41.jpg", "vid": null}}