{"video_url": "https://www.youtube.com/embed/-0NiqgJtluU?showinfo=0", "1": {"text": "Start with clean and dry hair.", "img": "https://www.wikihow.com/images/thumb/7/7b/Curl-Your-Hair-with-a-Straightener-Step-1-Version-4.jpg/v4-460px-Curl-Your-Hair-with-a-Straightener-Step-1-Version-4.jpg", "vid": null}, "2": {"text": "Use a thin flat iron.", "img": null, "vid": "/9/9a/Curl Your Hair with a Straightener Step 2 Version 3.360p.mp4"}, "3": {"text": "Apply heat protectant.", "img": null, "vid": "/1/1d/Curl Your Hair with a Straightener Step 3 Version 3.360p.mp4"}, "4": {"text": "Part your hair into sections.", "img": null, "vid": "/6/62/Curl Your Hair with a Straightener Step 4 Version 3.360p.mp4"}, "5": {"text": "Alternate flicks and curls.", "img": null, "vid": "/1/1b/Curl Your Hair with a Straightener Step 5 Version 3.360p.mp4"}, "6": {"text": "Make more pronounced curls by turning the straightener a full turn, instead of a half.", "img": null, "vid": "/7/7b/Curl Your Hair with a Straightener Step 6 Version 3.360p.mp4"}, "7": {"text": "Experiment with turning your straightener under and over.", "img": null, "vid": "/3/38/Curl Your Hair with a Straightener Step 7 Version 3.360p.mp4"}, "8": {"text": "Try flat waves.", "img": null, "vid": "/6/66/Curl Your Hair with a Straightener Step 8 Version 3.360p.mp4"}, "9": {"text": "Add some hairspray.", "img": null, "vid": "/8/8c/Curl Your Hair with a Straightener Step 9 Version 3.360p.mp4"}, "10": {"text": "Grab the section of hair you want to curl.", "img": null, "vid": "/f/f5/Curl Your Hair with a Straightener Step 10 Version 3.360p.mp4"}, "11": {"text": "Use one of the above techniques.", "img": null, "vid": "/5/59/Curl Your Hair with a Straightener Step 11 Version 3.360p.mp4"}, "12": {"text": "Finish up.", "img": null, "vid": "/4/44/Curl Your Hair with a Straightener Step 12 Version 3.360p.mp4"}}