{"video_url": "https://www.youtube.com/embed/ne-yZS5wkQM?showinfo=0", "1": {"text": " Remove your old nail polish", "img": null, "vid": "/e/e5/Do a French Manicure Step 1 Version 6.360p.mp4"}, "2": {"text": "French manicures look more striking with longer nails, so you don't want to trim them too close to your fingertips.", "img": null, "vid": "/f/ff/Do a French Manicure Step 2 Version 6.360p.mp4"}, "3": {"text": " File", "img": null, "vid": "/6/61/Do a French Manicure Step 3 Version 6.360p.mp4"}, "4": {"text": "Soak your nails.", "img": null, "vid": "/6/6e/Do a French Manicure Step 4 Version 3.360p.mp4"}, "5": {"text": "Push back your cuticles.", "img": null, "vid": "/2/29/Do a French Manicure Step 5 Version 6.360p.mp4"}, "6": {"text": "Apply the base coat.", "img": null, "vid": "/2/2e/Do a French Manicure Step 6 Version 6.360p.mp4"}, "7": {"text": "Paint your nail tips with white polish.", "img": null, "vid": "/a/a0/Do a French Manicure Step 7 Version 6.360p.mp4"}, "8": {"text": "Add a clear top coat to protect the look of your freshly painted nails.", "img": null, "vid": "/1/12/Do a French Manicure Step 8 Version 5.360p.mp4"}, "9": {"text": "Finished.", "img": "https://www.wikihow.com/images/thumb/4/48/Do-a-French-Manicure-Step-9-Version-6.jpg/v4-460px-Do-a-French-Manicure-Step-9-Version-6.jpg", "vid": null}, "10": {"text": "Use scotch tape.", "img": null, "vid": "/2/27/Do a French Manicure Step 10 Version 4.360p.mp4"}, "11": {"text": "Use moleskin pads.", "img": "https://www.wikihow.com/images/thumb/f/fc/Do-a-French-Manicure-Step-11-Version-3.jpg/v4-460px-Do-a-French-Manicure-Step-11-Version-3.jpg", "vid": null}, "12": {"text": "Try using white-out.", "img": "https://www.wikihow.com/images/thumb/5/55/Do-a-French-Manicure-Step-12-Version-5.jpg/v4-460px-Do-a-French-Manicure-Step-12-Version-5.jpg", "vid": null}}