{"video_url": "https://www.youtube.com/embed/MI36NvZcOzo?showinfo=0", "1": {"text": "Pick seed pods from existent cacti or buy commercial seeds.", "img": "https://www.wikihow.com/images/thumb/8/8b/Grow-a-Cactus-Step-1-Version-4.jpg/v4-460px-Grow-a-Cactus-Step-1-Version-4.jpg", "vid": null}, "2": {"text": "If harvesting seeds from cactus pods, gather the pods.", "img": null, "vid": "/b/b9/Grow a Cactus Step 2 Version 2.360p.mp4"}, "3": {"text": "Next, harvest the seeds from the pods.", "img": null, "vid": "/6/67/Grow a Cactus Step 3 Version 2.360p.mp4"}, "4": {"text": "Plant the seeds in high-drainage soil.", "img": null, "vid": "/d/db/Grow a Cactus Step 4 Version 2.360p.mp4"}, "5": {"text": "Cover the container and expose it to sun.", "img": null, "vid": "/f/f3/Grow a Cactus Step 5 Version 2.360p.mp4"}, "6": {"text": "Keep tropical cacti at a steady, warm temperature.", "img": null, "vid": "/f/fd/Grow a Cactus Step 6 Version 2.360p.mp4"}, "7": {"text": "When the first spines show, allow the plant to ventilate.", "img": null, "vid": "/1/12/Grow a Cactus Step 7 Version 2.360p.mp4"}, "8": {"text": "Repot your cacti when they are well-established.", "img": null, "vid": "/a/a2/Grow a Cactus Step 8 Version 2.360p.mp4"}, "9": {"text": "Allow cacti to recover from repotting in the shade.", "img": null, "vid": "/d/d9/Grow a Cactus Step 9 Version 2.360p.mp4"}, "10": {"text": "Water", "img": null, "vid": "/c/c0/Grow a Cactus Step 10 Version 2.360p.mp4"}, "11": {"text": "Fertilize young plants during the growing months.", "img": null, "vid": "/1/1c/Grow a Cactus Step 11 Version 2.360p.mp4"}, "12": {"text": "Prevent rot by avoiding over-watering.", "img": null, "vid": "/d/d5/Grow a Cactus Step 12 Version 2.360p.mp4"}, "13": {"text": "Gradually increase exposure to sunlight to treat etiolation.", "img": null, "vid": "/9/9b/Grow a Cactus Step 13 Version 2.360p.mp4"}, "14": {"text": "Avoid phototoxicity by limiting sun exposure after using pesticides.", "img": null, "vid": "/2/26/Grow a Cactus Step 14 Version 2.360p.mp4"}, "15": {"text": "Don't be frightened by natural \"corking\".", "img": null, "vid": "/4/49/Grow a Cactus Step 15 Version 2.360p.mp4"}}