{"video_url": "https://www.youtube.com/embed/1A3RfVS1L_4?showinfo=0", "1": {"text": "Measure out 2 cups (240 g) of powdered sugar into a mixing bowl.", "img": "https://www.wikihow.com/images/thumb/4/4e/Make-Donut-Glaze-Step-1.jpg/v4-460px-Make-Donut-Glaze-Step-1.jpg", "vid": null}, "2": {"text": "Stir 1\u20444\u00a0\u00a0c (59\u00a0mL) of milk into the powdered sugar using a whisk.", "img": null, "vid": "/8/8b/Make Donut Glaze Step 2.360p.mp4"}, "3": {"text": "Mix in 1\u20444\u00a0\u00a0tsp (1.2\u00a0mL) of vanilla extract and a pinch of salt.", "img": null, "vid": "/2/29/Make Donut Glaze Step 3.360p.mp4"}, "4": {"text": "Dip your donuts into the glaze and put them on a rack until the glaze hardens.", "img": null, "vid": "/2/25/Make Donut Glaze Step 4.360p.mp4"}, "5": {"text": "Set up a double boiler", "img": "https://www.wikihow.com/images/thumb/8/82/Make-Donut-Glaze-Step-5.jpg/v4-460px-Make-Donut-Glaze-Step-5.jpg", "vid": null}, "6": {"text": "Heat chocolate chips, butter, and corn syrup in the bowl over medium heat.", "img": null, "vid": "/7/7e/Make Donut Glaze Step 6.360p.mp4"}, "7": {"text": "Stir the ingredients often until they are melted and thoroughly combined.", "img": null, "vid": "/e/e7/Make Donut Glaze Step 7.360p.mp4"}, "8": {"text": "Stir in 1\u20444\u00a0\u00a0tsp (1.2\u00a0mL) of vanilla extract.", "img": "https://www.wikihow.com/images/thumb/e/e4/Make-Donut-Glaze-Step-8.jpg/v4-460px-Make-Donut-Glaze-Step-8.jpg", "vid": null}, "9": {"text": "Dip the tops of your donuts into the glaze and place them on a rack.", "img": null, "vid": "/a/a2/Make Donut Glaze Step 9.360p.mp4"}, "10": {"text": "Blend 1 cup (170 g) of brown sugar in a blender until it becomes powdery.", "img": null, "vid": "/4/46/Make Donut Glaze Step 10.360p.mp4"}, "11": {"text": "Combine the sugar with unsweetened soy milk and vanilla extract in a bowl.", "img": null, "vid": "/b/be/Make Donut Glaze Step 11.360p.mp4"}, "12": {"text": "Use this glaze to top vegan donuts or other vegan desserts.", "img": null, "vid": "/4/46/Make Donut Glaze Step 12.360p.mp4"}}