{"video_url": "https://www.youtube.com/embed/FFBjBvNP9YI?showinfo=0", "1": {"text": "Know that cup size is not absolute.", "img": null, "vid": "/7/76/Measure Your Bra Size Step 1 Version 2.360p.mp4"}, "2": {"text": "Understand how a correctly fitted bra should look and feel.", "img": null, "vid": "/c/c0/Measure Your Bra Size Step 2 Version 2.360p.mp4"}, "3": {"text": "Be aware of different breast shapes.", "img": null, "vid": "/7/77/Measure Your Bra Size Step 3 Version 2.360p.mp4"}, "4": {"text": "Know about sister sizes.", "img": null, "vid": "/f/f2/Measure Your Bra Size Step 4 Version 2.360p.mp4"}, "5": {"text": "Navigate different fitting styles.", "img": null, "vid": "/8/87/Measure Your Bra Size Step 5 Version 2.360p.mp4"}, "6": {"text": "Be wary of professional fittings.", "img": null, "vid": "/3/35/Measure Your Bra Size Step 6 Version 2.360p.mp4"}, "7": {"text": "Measure your band size.", "img": null, "vid": "/3/3a/Measure Your Bra Size Step 7 Version 2.360p.mp4"}, "8": {"text": "Determine your cup size.", "img": null, "vid": "/a/a9/Measure Your Bra Size Step 8 Version 2.360p.mp4"}, "9": {"text": "Try on a bra with the band and cup size you've arrived at in these steps.", "img": null, "vid": "/6/6b/Measure Your Bra Size Step 11 Version 2.360p.mp4"}, "10": {"text": "Put on the bra on correctly.", "img": null, "vid": "/c/c3/Measure Your Bra Size Step 12 Version 2.360p.mp4"}, "11": {"text": "Check the band size.", "img": null, "vid": "/b/bf/Measure Your Bra Size Step 13 Version 2.360p.mp4"}, "12": {"text": "Check the cup size.", "img": null, "vid": "/4/48/Measure Your Bra Size Step 14 Version 2.360p.mp4"}, "13": {"text": "See how it looks with your top on.", "img": null, "vid": "/c/c7/Measure Your Bra Size Step 15 Version 2.360p.mp4"}, "14": {"text": "Measure your band size.", "img": null, "vid": "/7/75/Measure Your Bra Size Step 9 Version 2.360p.mp4"}, "15": {"text": "Measure your cup size.", "img": null, "vid": "/8/89/Measure Your Bra Size Step 10 Version 2.360p.mp4"}}