{"video_url": "https://www.youtube.com/embed/JCfDQzMkENw?showinfo=0", "1": {"text": "Put on a pair of socks.", "img": null, "vid": "/8/80/Moonwalk Step 1 Version 3.360p.mp4"}, "2": {"text": "Find a smooth surface.", "img": null, "vid": "/a/ac/Moonwalk Step 2 Version 3.360p.mp4"}, "3": {"text": "Place one foot directly in front of the other and stand on the toes of your back leg.", "img": null, "vid": "/f/fa/Moonwalk Step 3 Version 3.360p.mp4"}, "4": {"text": "Keep your balance.", "img": null, "vid": "/3/3d/Moonwalk Step 4 Version 3.360p.mp4"}, "5": {"text": "Slide your left heel back", "img": null, "vid": "/6/60/Moonwalk Step 5 Version 3.360p.mp4"}, "6": {"text": "Snap the heel", "img": null, "vid": "/3/3d/Moonwalk Step 6 Version 3.360p.mp4"}, "7": {"text": "Repeat the previous two steps, switching the roles of your left and right foot.", "img": null, "vid": "/4/44/Moonwalk Step 7 Version 3.360p.mp4"}, "8": {"text": "Add some frills.", "img": null, "vid": "/f/f6/Moonwalk Step 8 Version 3.360p.mp4"}}