{"video_url": "https://www.youtube.com/embed/3Z55rGnR_Os", "1": {"text": "Make sure your tortilla is large enough for its contents.", "img": null, "vid": "/f/fd/Roll a Burrito Step 1 Version 3.360p.mp4"}, "2": {"text": "Put some moisture into your tortilla.", "img": null, "vid": "/3/33/Roll a Burrito Step 2 Version 3.360p.mp4"}, "3": {"text": "Carefully add the contents of the burrito to the center of the tortilla.", "img": null, "vid": "/a/ab/Roll a Burrito Step 3 Version 3.360p.mp4"}, "4": {"text": "Join the front and bottom flap and quickly lift the tortilla into the air.", "img": null, "vid": "/5/53/Roll a Burrito Step 4 Version 3.360p.mp4"}, "5": {"text": "Pull the left flap of the tortilla over the burrito contents, toward the center.", "img": null, "vid": "/a/ac/Roll a Burrito Step 5 Version 3.360p.mp4"}, "6": {"text": "Pull the right flap of the tortilla over the burrito contents, toward the center.", "img": null, "vid": "/4/4e/Roll a Burrito Step 6 Version 3.360p.mp4"}, "7": {"text": "Tuck the top flap of the tortilla underneath the burrito contents using one or two hands.", "img": null, "vid": "/d/dc/Roll a Burrito Step 7 Version 3.360p.mp4"}, "8": {"text": "Starting from your body and moving outward, roll the burrito forward.", "img": null, "vid": "/c/cf/Roll a Burrito Step 8 Version 3.360p.mp4"}, "9": {"text": "Wrap the burrito in foil.", "img": null, "vid": "/6/67/Roll a Burrito Step 9 Version 3.360p.mp4"}, "10": {"text": "Put some moisture into your tortilla.", "img": null, "vid": "/e/e1/Roll a Burrito Step 10 Version 3.360p.mp4"}, "11": {"text": "Carefully add the contents of the burrito to the center of the tortilla, being careful not to overload.", "img": null, "vid": "/3/3e/Roll a Burrito Step 11 Version 3.360p.mp4"}, "12": {"text": "Fold the left and right sides of the tortilla toward the center.", "img": null, "vid": "/7/75/Roll a Burrito Step 12 Version 3.360p.mp4"}, "13": {"text": "Grab the bottom flap of the tortilla and tuck it over and then under the contents of the burrito.", "img": null, "vid": "/7/70/Roll a Burrito Step 13 Version 3.360p.mp4"}, "14": {"text": "Continue rolling the tortilla until it assumes its traditional cylinder.", "img": null, "vid": "/a/a2/Roll a Burrito Step 14 Version 3.360p.mp4"}, "15": {"text": "Wrap the burrito in foil.", "img": null, "vid": "/a/a4/Roll a Burrito Step 15 Version 3.360p.mp4"}}