{"video_url": "https://www.youtube.com/embed/Yztn5wwOOcc", "1": {"text": "Choose the right wrap.", "img": "https://www.wikihow.com/images/thumb/a/ab/Wrap-Your-Hands-for-Boxing-Step-1-Version-2.jpg/v4-460px-Wrap-Your-Hands-for-Boxing-Step-1-Version-2.jpg", "vid": null}, "2": {"text": "Wrap with the correct tension.", "img": null, "vid": "/5/58/Wrap Your Hands for Boxing Step 2 Version 3.360p.mp4"}, "3": {"text": "Keep the wraps free of wrinkles.", "img": null, "vid": "/5/55/Wrap Your Hands for Boxing Step 3 Version 2.360p.mp4"}, "4": {"text": "Keep your wrists straight when you wrap them.", "img": "https://www.wikihow.com/images/thumb/f/ff/Wrap-Your-Hands-for-Boxing-Step-4-Version-4.jpg/v4-460px-Wrap-Your-Hands-for-Boxing-Step-4-Version-4.jpg", "vid": null}, "5": {"text": "Stretch your hand out.", "img": null, "vid": "/c/c2/Wrap Your Hands for Boxing Step 5 Version 2.360p.mp4"}, "6": {"text": "Place your thumb through the hole at the end of the wrap.", "img": null, "vid": "/2/24/Wrap Your Hands for Boxing Step 6 Version 3.360p.mp4"}, "7": {"text": "Wrap your wrist.", "img": null, "vid": "/a/a2/Wrap Your Hands for Boxing Step 7 Version 3.360p.mp4"}, "8": {"text": "Wrap your hand.", "img": null, "vid": "/3/37/Wrap Your Hands for Boxing Step 8 Version 3.360p.mp4"}, "9": {"text": "Wrap your thumb.", "img": null, "vid": "/8/83/Wrap Your Hands for Boxing Step 9 Version 3.360p.mp4"}, "10": {"text": "Wrap your fingers.", "img": null, "vid": "/9/98/Wrap Your Hands for Boxing Step 10 Version 3.360p.mp4"}, "11": {"text": "Wrap your hand again.", "img": null, "vid": "/d/d7/Wrap Your Hands for Boxing Step 11 Version 3.360p.mp4"}, "12": {"text": "Secure the wrap.", "img": null, "vid": "/e/e8/Wrap Your Hands for Boxing Step 12 Version 3.360p.mp4"}, "13": {"text": "Repeat with the other hand.", "img": "https://www.wikihow.com/images/thumb/4/46/Wrap-Your-Hands-for-Boxing-Step-13-Version-3.jpg/v4-460px-Wrap-Your-Hands-for-Boxing-Step-13-Version-3.jpg", "vid": null}}